LICENSE
MANIFEST.in
README.md
setup.py
InstagramAPI/__init__.py
InstagramAPI/src/Checkpoint.py
InstagramAPI/src/Constants.py
InstagramAPI/src/Instagram.py
InstagramAPI/src/InstagramException.py
InstagramAPI/src/InstagramRegistration.py
InstagramAPI/src/SignatureUtils.py
InstagramAPI/src/__init__.py
InstagramAPI/src/Utils/Settings.py
InstagramAPI/src/Utils/Utils.py
InstagramAPI/src/Utils/__init__.py
InstagramAPI/src/Utils/php.py
InstagramAPI/src/http/HttpInterface.py
InstagramAPI/src/http/UserAgent.py
InstagramAPI/src/http/__init__.py
InstagramAPI/src/http/Response/AccountCreationResponse.py
InstagramAPI/src/http/Response/ChallengeResponse.py
InstagramAPI/src/http/Response/CheckEmailResponse.py
InstagramAPI/src/http/Response/CheckUsernameResponse.py
InstagramAPI/src/http/Response/Comment.py
InstagramAPI/src/http/Response/ConfigureResponse.py
InstagramAPI/src/http/Response/ConfigureVideoResponse.py
InstagramAPI/src/http/Response/FollowerResponse.py
InstagramAPI/src/http/Response/FollowingResponse.py
InstagramAPI/src/http/Response/HdProfilePicUrlInfo.py
InstagramAPI/src/http/Response/Location.py
InstagramAPI/src/http/Response/LocationResponse.py
InstagramAPI/src/http/Response/LoginResponse.py
InstagramAPI/src/http/Response/MediaInfoResponse.py
InstagramAPI/src/http/Response/MediaLikersResponse.py
InstagramAPI/src/http/Response/Response.py
InstagramAPI/src/http/Response/UploadJobVideoResponse.py
InstagramAPI/src/http/Response/UploadPhotoResponse.py
InstagramAPI/src/http/Response/UploadVideoResponse.py
InstagramAPI/src/http/Response/User.py
InstagramAPI/src/http/Response/UsernameInfoResponse.py
InstagramAPI/src/http/Response/UsernameSuggestionsResponse.py
InstagramAPI/src/http/Response/__init__.py
instagram_python.egg-info/PKG-INFO
instagram_python.egg-info/SOURCES.txt
instagram_python.egg-info/dependency_links.txt
instagram_python.egg-info/not-zip-safe
instagram_python.egg-info/requires.txt
instagram_python.egg-info/top_level.txt