Metadata-Version: 1.1
Name: instagram-python
Version: 1.4
Summary: Instagram private API PHP
Home-page: https://github.com/danleyb2/Instagram-API
Author: Nyaundi Brian
Author-email: ndieksman@gmail.com
License: MIT
Keywords: Instagram Private API Python
Platform: any
Classifier: Environment :: Console
Classifier: Intended Audience :: Developers
Classifier: License :: OSI Approved :: MIT License
Classifier: Operating System :: OS Independent
Classifier: Programming Language :: Python
Classifier: Programming Language :: Python :: 2.7
